.gitignore
LICENSE.txt
MANIFEST.in
Makefile
README.md
requirements.txt
setup.py
pypassvault/__init__.py
pypassvault/passvault.py
pypassvault.egg-info/PKG-INFO
pypassvault.egg-info/SOURCES.txt
pypassvault.egg-info/dependency_links.txt
pypassvault.egg-info/entry_points.txt
pypassvault.egg-info/requires.txt
pypassvault.egg-info/top_level.txt
tests/__init__.py
tests/context.py
tests/test_advanced.py
tests/test_basic.py