Metadata-Version: 2.1
Name: pypassvault
Version: 0.1.4
Summary: A simple commandline password vault written in python.
Home-page: https://github.com/cryptbytestech/pypassvault
Author: cryptbytestech
Author-email: cryptbytestech@gmail.com
License: MIT
Keywords: password vault program cryptography
Platform: UNKNOWN
Classifier: Development Status :: 3 - Alpha
Classifier: Intended Audience :: Developers
Classifier: License :: OSI Approved :: MIT License
Classifier: Programming Language :: Python :: 3.6
